g3dtools-0.2.3.data/scripts/g3dtools
utils/Utils.py
utils/UtilsV1.py
utils/__init__.py
utils/binning.py
utils/version.py
g3dtools-0.2.3.dist-info/LICENSE
g3dtools-0.2.3.dist-info/METADATA
g3dtools-0.2.3.dist-info/WHEEL
g3dtools-0.2.3.dist-info/top_level.txt
g3dtools-0.2.3.dist-info/RECORD
