Metadata-Version: 2.1
Name: g3dtools
Version: 0.2.3
Summary: Generate and query genome 3D stucture (.g3d) file
Home-page: https://github.com/lidaof/g3d
Author: Daofeng Li
Author-email: lidaof@gmail.com
License: UNKNOWN
Platform: UNKNOWN
Classifier: Programming Language :: Python :: 3
Classifier: License :: OSI Approved :: MIT License
Classifier: Operating System :: OS Independent
License-File: LICENSE
Requires-Dist: msgpack
